src/cctp-client/__init__.py
src/cctp-client/example.py
cctp_client-0.0.1.dist-info/METADATA
cctp_client-0.0.1.dist-info/WHEEL
cctp_client-0.0.1.dist-info/licenses/LICENSE
cctp_client-0.0.1.dist-info/RECORD
