Metadata-Version: 2.1
Name: cctp-client
Version: 0.0.1
Summary: A library for interacting with CCTP
Project-URL: Homepage, https://github.com/cctp-money/cctp-client
Project-URL: Bug Tracker, https://github.com/cctp-money/cctp-client/issues
Author-email: bd21 <bd21@uw.edu>
License-File: LICENSE
Classifier: Operating System :: OS Independent
Classifier: Programming Language :: Python :: 3
Requires-Python: >=3.8
